{
  "?xml": {
    "@_version": "1.0",
    "@_encoding": "utf-8"
  },
  "macros": {
    "macro": [
      {
        "component": {
          "@_ref": "standardcluster"
        },
        "connections": {
          "connection": [
            {
              "offset": {
                "position": {
                  "@_x": "3.503824e+07",
                  "@_y": "0",
                  "@_z": "5.510629e+07"
                }
              },
              "macro": {
                "@_ref": "Cluster_500_Sector001_macro",
                "@_connection": "cluster"
              },
              "@_name": "Cluster_500_Sector001_connection",
              "@_ref": "sectors"
            },
            {
              "offset": {
                "position": {
                  "@_x": "3.503824e+07",
                  "@_y": "-20000",
                  "@_z": "5.510629e+07"
                }
              },
              "macro": {
                "component": {
                  "@_connection": "cluster",
                  "@_ref": "standardregion"
                },
                "properties": {
                  "region": {
                    "@_ref": "s2_grav"
                  }
                },
                "@_name": "Cluster500_Sector001_Region002_macro"
              },
              "@_name": "Cluster500_Sector001_Region002_connection",
              "@_ref": "regions"
            },
            {
              "offset": {
                "position": {
                  "@_x": "3.503824e+07",
                  "@_y": "-20000",
                  "@_z": "5.510629e+07"
                }
              },
              "macro": {
                "component": {
                  "@_connection": "cluster",
                  "@_ref": "standardregion"
                },
                "properties": {
                  "region": {
                    "@_ref": "wave_asteroids"
                  }
                },
                "@_name": "Cluster500_Sector001_Region003_macro"
              },
              "@_name": "Cluster500_Sector001_Region003_connection",
              "@_ref": "regions"
            },
            {
              "offset": {
                "position": {
                  "@_x": "3.503824e+07",
                  "@_y": "-20000",
                  "@_z": "5.510629e+07"
                }
              },
              "macro": {
                "component": {
                  "@_connection": "cluster",
                  "@_ref": "standardregion"
                },
                "properties": {
                  "region": {
                    "@_ref": "wave_active"
                  }
                },
                "@_name": "Cluster500_Sector001_Region004_macro"
              },
              "@_name": "Cluster500_Sector001_Region004_connection",
              "@_ref": "regions"
            },
            {
              "offset": {
                "position": {
                  "@_x": "986167.6",
                  "@_y": "0",
                  "@_z": "-2.108045e+08"
                }
              },
              "macro": {
                "@_ref": "Cluster_500_Sector002_macro",
                "@_connection": "cluster"
              },
              "@_name": "Cluster_500_Sector002_connection",
              "@_ref": "sectors"
            },
            {
              "offset": {
                "position": {
                  "@_x": "926458",
                  "@_y": "-20000",
                  "@_z": "-210862000"
                }
              },
              "macro": {
                "component": {
                  "@_connection": "cluster",
                  "@_ref": "standardregion"
                },
                "properties": {
                  "region": {
                    "@_ref": "s2_grav_small"
                  }
                },
                "@_name": "Cluster500_Sector002_Region001_macro"
              },
              "@_name": "Cluster500_Sector002_Region001_connection",
              "@_ref": "regions"
            },
            {
              "offset": {
                "position": {
                  "@_x": "1015770",
                  "@_y": "-15000",
                  "@_z": "-210920000"
                }
              },
              "macro": {
                "component": {
                  "@_connection": "cluster",
                  "@_ref": "standardregion"
                },
                "properties": {
                  "region": {
                    "@_ref": "s2_grav_small_v2"
                  }
                },
                "@_name": "Cluster500_Sector002_Region002_macro"
              },
              "@_name": "Cluster500_Sector002_Region002_connection",
              "@_ref": "regions"
            },
            {
              "offset": {
                "position": {
                  "@_x": "1089160",
                  "@_y": "-15000",
                  "@_z": "-210893000"
                }
              },
              "macro": {
                "component": {
                  "@_connection": "cluster",
                  "@_ref": "standardregion"
                },
                "properties": {
                  "region": {
                    "@_ref": "s2_grav_small_v2"
                  }
                },
                "@_name": "Cluster500_Sector002_Region003_macro"
              },
              "@_name": "Cluster500_Sector002_Region003_connection",
              "@_ref": "regions"
            },
            {
              "offset": {
                "position": {
                  "@_x": "-1.103792e+08",
                  "@_y": "0",
                  "@_z": "-4.594556e+07"
                }
              },
              "macro": {
                "@_ref": "Cluster_500_Sector003_macro",
                "@_connection": "cluster"
              },
              "@_name": "Cluster_500_Sector003_connection",
              "@_ref": "sectors"
            },
            {
              "offset": {
                "position": {
                  "@_x": "-3.767219e+07",
                  "@_y": "0",
                  "@_z": "4580365"
                }
              },
              "macro": {
                "connections": {
                  "connection": [
                    {
                      "macro": {
                        "@_ref": "tzoneCluster_500_Sector001SHCon6_GateZone_macro",
                        "@_path": "../../Cluster_500_Sector001_connection/tzoneCluster_500_Sector001SHCon6_GateZone_connection",
                        "@_connection": "exitpoint1"
                      },
                      "@_ref": "entrypoint"
                    },
                    {
                      "macro": {
                        "@_ref": "tzoneCluster_500_Sector003SHCon5_GateZone_macro",
                        "@_path": "../../Cluster_500_Sector003_connection/tzoneCluster_500_Sector003SHCon5_GateZone_connection",
                        "@_connection": "entrypoint1"
                      },
                      "@_ref": "exitpoint"
                    }
                  ]
                },
                "@_ref": "SuperHighway01_Cluster500_macro",
                "@_connection": "cluster"
              },
              "@_name": "SuperHighway01_Cluster500_connection",
              "@_ref": "sechighways"
            },
            {
              "offset": {
                "position": {
                  "@_x": "-3.766836e+07",
                  "@_y": "0",
                  "@_z": "4580365"
                }
              },
              "macro": {
                "connections": {
                  "connection": [
                    {
                      "macro": {
                        "@_ref": "tzoneCluster_500_Sector001SHCon10_GateZone_macro",
                        "@_path": "../../Cluster_500_Sector001_connection/tzoneCluster_500_Sector001SHCon10_GateZone_connection",
                        "@_connection": "entrypoint1"
                      },
                      "@_ref": "exitpoint"
                    },
                    {
                      "macro": {
                        "@_ref": "tzoneCluster_500_Sector003SHCon9_GateZone_macro",
                        "@_path": "../../Cluster_500_Sector003_connection/tzoneCluster_500_Sector003SHCon9_GateZone_connection",
                        "@_connection": "exitpoint1"
                      },
                      "@_ref": "entrypoint"
                    }
                  ]
                },
                "@_ref": "SuperHighway02_Cluster500_macro",
                "@_connection": "cluster"
              },
              "@_name": "SuperHighway02_Cluster500_connection",
              "@_ref": "sechighways"
            },
            {
              "offset": {
                "position": {
                  "@_x": "18020700",
                  "@_y": "0",
                  "@_z": "-77853100"
                }
              },
              "macro": {
                "connections": {
                  "connection": [
                    {
                      "macro": {
                        "@_ref": "tzoneCluster_500_Sector001SHCon2_GateZone_macro",
                        "@_path": "../../Cluster_500_Sector001_connection/tzoneCluster_500_Sector001SHCon2_GateZone_connection",
                        "@_connection": "exitpoint1"
                      },
                      "@_ref": "entrypoint"
                    },
                    {
                      "macro": {
                        "@_ref": "tzoneCluster_500_Sector002SHCon5_GateZone_macro",
                        "@_path": "../../Cluster_500_Sector002_connection/tzoneCluster_500_Sector002SHCon5_GateZone_connection",
                        "@_connection": "entrypoint1"
                      },
                      "@_ref": "exitpoint"
                    }
                  ]
                },
                "@_ref": "SuperHighway03_Cluster500_macro",
                "@_connection": "cluster"
              },
              "@_name": "SuperHighway03_Cluster500_connection",
              "@_ref": "sechighways"
            },
            {
              "offset": {
                "position": {
                  "@_x": "18024300",
                  "@_y": "0",
                  "@_z": "-77853100"
                }
              },
              "macro": {
                "connections": {
                  "connection": [
                    {
                      "macro": {
                        "@_ref": "tzoneCluster_500_Sector002SHCon9_GateZone_macro",
                        "@_path": "../../Cluster_500_Sector002_connection/tzoneCluster_500_Sector002SHCon9_GateZone_connection",
                        "@_connection": "exitpoint1"
                      },
                      "@_ref": "entrypoint"
                    },
                    {
                      "macro": {
                        "@_ref": "tzoneCluster_500_Sector001SHCon4_GateZone_macro",
                        "@_path": "../../Cluster_500_Sector001_connection/tzoneCluster_500_Sector001SHCon4_GateZone_connection",
                        "@_connection": "entrypoint1"
                      },
                      "@_ref": "exitpoint"
                    }
                  ]
                },
                "@_ref": "SuperHighway04_Cluster500_macro",
                "@_connection": "cluster"
              },
              "@_name": "SuperHighway04_Cluster500_connection",
              "@_ref": "sechighways"
            },
            {
              "macro": {
                "component": {
                  "@_ref": "Cluster_500t8",
                  "@_connection": "space"
                },
                "properties": {
                  "phases": {
                    "phase": [
                      {
                        "transitions": {
                          "transition": {
                            "@_id": "warning",
                            "@_trigger": "wave_activatewarning",
                            "@_duration": "60"
                          }
                        },
                        "@_id": "calm",
                        "@_path": "wave_inactive",
                        "@_duration": "3",
                        "@_loop": "true"
                      },
                      {
                        "transitions": {
                          "transition": [
                            {
                              "@_id": "calm",
                              "@_trigger": "wave_deactivatewarning",
                              "@_duration": "60"
                            },
                            {
                              "@_id": "wave",
                              "@_trigger": "wave_activatewave",
                              "@_duration": "0"
                            }
                          ]
                        },
                        "@_id": "warning",
                        "@_path": "wave_warningactivating",
                        "@_duration": "60",
                        "@_loop": "true"
                      },
                      {
                        "transitions": {
                          "transition": {
                            "@_id": "calm",
                            "@_duration": "0"
                          }
                        },
                        "propagation": {
                          "@_part": "anim_sun_core",
                          "@_speed": "16300000"
                        },
                        "@_id": "wave",
                        "@_path": "wave_active",
                        "@_duration": "120"
                      }
                    ],
                    "@_default": "calm"
                  }
                }
              },
              "@_ref": "content"
            }
          ]
        },
        "@_name": "Cluster_500_macro",
        "@_class": "cluster"
      },
      {
        "component": {
          "@_ref": "standardcluster"
        },
        "connections": {
          "connection": [
            {
              "macro": {
                "@_ref": "Cluster_501_Sector001_macro",
                "@_connection": "cluster"
              },
              "@_name": "Cluster_501_Sector001_connection",
              "@_ref": "sectors"
            },
            {
              "offset": {
                "position": {
                  "@_x": "0",
                  "@_y": "-20000",
                  "@_z": "0"
                }
              },
              "macro": {
                "component": {
                  "@_connection": "cluster",
                  "@_ref": "standardregion"
                },
                "properties": {
                  "region": {
                    "@_ref": "region_c501s01_base"
                  }
                },
                "@_name": "Cluster501_Sector001_Region001_macro"
              },
              "@_name": "Cluster501_Sector001_Region001_connection",
              "@_ref": "regions"
            },
            {
              "macro": {
                "component": {
                  "@_ref": "Cluster_501t6",
                  "@_connection": "space"
                }
              },
              "@_ref": "content"
            }
          ]
        },
        "@_name": "Cluster_501_macro",
        "@_class": "cluster"
      },
      {
        "component": {
          "@_ref": "standardcluster"
        },
        "connections": {
          "connection": [
            {
              "macro": {
                "@_ref": "Cluster_502_Sector001_macro",
                "@_connection": "cluster"
              },
              "@_name": "Cluster_502_Sector001_connection",
              "@_ref": "sectors"
            },
            {
              "offset": {
                "position": {
                  "@_x": "0",
                  "@_y": "-20000",
                  "@_z": "0"
                }
              },
              "macro": {
                "component": {
                  "@_connection": "cluster",
                  "@_ref": "standardregion"
                },
                "properties": {
                  "region": {
                    "@_ref": "region_c502s01_base"
                  }
                },
                "@_name": "Cluster502_Sector001_Region001_macro"
              },
              "@_name": "Cluster502_Sector001_Region001_connection",
              "@_ref": "regions"
            },
            {
              "offset": {
                "position": {
                  "@_x": "47000.0",
                  "@_y": "-5000",
                  "@_z": "172000.0"
                }
              },
              "macro": {
                "component": {
                  "@_connection": "cluster",
                  "@_ref": "standardregion"
                },
                "properties": {
                  "region": {
                    "@_ref": "region_c502s01_scrap"
                  }
                },
                "@_name": "Cluster502_Sector001_Region002_macro"
              },
              "@_name": "Cluster502_Sector001_Region002_connection",
              "@_ref": "regions"
            },
            {
              "macro": {
                "component": {
                  "@_ref": "Cluster_502t6",
                  "@_connection": "space"
                }
              },
              "@_ref": "content"
            }
          ]
        },
        "@_name": "Cluster_502_macro",
        "@_class": "cluster"
      },
      {
        "component": {
          "@_ref": "standardcluster"
        },
        "connections": {
          "connection": [
            {
              "macro": {
                "@_ref": "Cluster_503_Sector001_macro",
                "@_connection": "cluster"
              },
              "@_name": "Cluster_503_Sector001_connection",
              "@_ref": "sectors"
            },
            {
              "offset": {
                "position": {
                  "@_x": "0",
                  "@_y": "-100000",
                  "@_z": "0"
                }
              },
              "macro": {
                "component": {
                  "@_connection": "cluster",
                  "@_ref": "standardregion"
                },
                "properties": {
                  "region": {
                    "@_ref": "region_c503s01_base"
                  }
                },
                "@_name": "Cluster503_Sector001_Region001_macro"
              },
              "@_name": "Cluster503_Sector001_Region001_connection",
              "@_ref": "regions"
            },
            {
              "offset": {
                "position": {
                  "@_x": "41900.991",
                  "@_y": "-22000",
                  "@_z": "48366"
                }
              },
              "macro": {
                "component": {
                  "@_connection": "cluster",
                  "@_ref": "standardregion"
                },
                "properties": {
                  "region": {
                    "@_ref": "region_c503s01_casino"
                  }
                },
                "@_name": "Cluster503_Sector001_Region002_macro"
              },
              "@_name": "Cluster503_Sector001_Region002_connection",
              "@_ref": "regions"
            },
            {
              "offset": {
                "position": {
                  "@_x": "41900.991",
                  "@_y": "-42000",
                  "@_z": "48366"
                }
              },
              "macro": {
                "component": {
                  "@_connection": "cluster",
                  "@_ref": "standardregion"
                },
                "properties": {
                  "region": {
                    "@_ref": "region_c503s01_casino2"
                  }
                },
                "@_name": "Cluster503_Sector001_Region003_macro"
              },
              "@_name": "Cluster503_Sector001_Region003_connection",
              "@_ref": "regions"
            },
            {
              "offset": {
                "position": {
                  "@_x": "41900.991",
                  "@_y": "-7000",
                  "@_z": "48366"
                }
              },
              "macro": {
                "component": {
                  "@_connection": "cluster",
                  "@_ref": "standardregion"
                },
                "properties": {
                  "region": {
                    "@_ref": "region_c503s01_casino3"
                  }
                },
                "@_name": "Cluster503_Sector001_Region004_macro"
              },
              "@_name": "Cluster503_Sector001_Region004_connection",
              "@_ref": "regions"
            },
            {
              "macro": {
                "component": {
                  "@_ref": "Cluster_503t6",
                  "@_connection": "space"
                }
              },
              "@_ref": "content"
            }
          ]
        },
        "@_name": "Cluster_503_macro",
        "@_class": "cluster"
      },
      {
        "component": {
          "@_ref": "standardcluster"
        },
        "connections": {
          "connection": [
            {
              "macro": {
                "@_ref": "Cluster_504_Sector001_macro",
                "@_connection": "cluster"
              },
              "@_name": "Cluster_504_Sector001_connection",
              "@_ref": "sectors"
            },
            {
              "macro": {
                "component": {
                  "@_ref": "Cluster_504t4",
                  "@_connection": "space"
                }
              },
              "@_ref": "content"
            },
            {
              "offset": {
                "position": {
                  "@_x": "0",
                  "@_y": "-20000",
                  "@_z": "0"
                }
              },
              "macro": {
                "component": {
                  "@_connection": "cluster",
                  "@_ref": "standardregion"
                },
                "properties": {
                  "region": {
                    "@_ref": "region504_grav"
                  }
                },
                "@_name": "Cluster504_Sector001_Region002_macro"
              },
              "@_name": "Cluster504_Sector001_Region002_connection",
              "@_ref": "regions"
            },
            {
              "offset": {
                "position": {
                  "@_x": "0",
                  "@_y": "-20000",
                  "@_z": "0"
                }
              },
              "macro": {
                "component": {
                  "@_connection": "cluster",
                  "@_ref": "standardregion"
                },
                "properties": {
                  "region": {
                    "@_ref": "region504_asteroids"
                  }
                },
                "@_name": "Cluster504_Sector001_Region003_macro"
              },
              "@_name": "Cluster504_Sector001_Region003_connection",
              "@_ref": "regions"
            },
            {
              "offset": {
                "position": {
                  "@_x": "0",
                  "@_y": "-20000",
                  "@_z": "0"
                }
              },
              "macro": {
                "component": {
                  "@_connection": "cluster",
                  "@_ref": "standardregion"
                },
                "properties": {
                  "region": {
                    "@_ref": "region504wave_active"
                  }
                },
                "@_name": "Cluster504_Sector001_Region004_macro"
              },
              "@_name": "Cluster504_Sector001_Region004_connection",
              "@_ref": "regions"
            }
          ]
        },
        "@_name": "Cluster_504_macro",
        "@_class": "cluster"
      }
    ]
  }
}